mentat/__init__.py
mentat/cli.py
mentat/config.py
mentat/creds.py
mentat_bot-1.1.3.dist-info/LICENSE
mentat_bot-1.1.3.dist-info/METADATA
mentat_bot-1.1.3.dist-info/WHEEL
mentat_bot-1.1.3.dist-info/entry_points.txt
mentat_bot-1.1.3.dist-info/top_level.txt
mentat_bot-1.1.3.dist-info/RECORD
