Metadata-Version: 2.2
Name: mentat-bot
Version: 1.1.3
Summary: Discord bot designed to streamline credential management and access tracking during red team engagements.
Requires-Python: <3.13,>=3.12
License-File: LICENSE
Requires-Dist: asyncclick>=8.1.8
Requires-Dist: discord-py>=2.4.0
Requires-Dist: paramiko>=3.5.1
Requires-Dist: python-json-logger>=3.2.1
Requires-Dist: pyyaml>=6.0.2
Requires-Dist: rich>=13.9.4
